dtcc_data/__init__.py
dtcc_data/cache.py
dtcc_data/division.py
dtcc_data/geopkg.py
dtcc_data/lidar.py
dtcc_data/multiplication.py
dtcc_data/overpass.py
dtcc_data/wrapper.py
dtcc_data/scripts/main.py
dtcc_data-0.9.1.dist-info/LICENSE
dtcc_data-0.9.1.dist-info/METADATA
dtcc_data-0.9.1.dist-info/WHEEL
dtcc_data-0.9.1.dist-info/entry_points.txt
dtcc_data-0.9.1.dist-info/top_level.txt
dtcc_data-0.9.1.dist-info/RECORD
