Metadata-Version: 2.2
Name: dtcc-data
Version: 0.9.1
Summary: DTCC Data
Author-email: Anders Logg <logg@chalmers.se>, Vasilis Naserentin <vasilis.naserentin@chalmers.se>, Dag Wästberg <dwastberg@gmail.com>, Themistoklis Arvanitis <thearva@chalmers.se>
Classifier: Intended Audience :: Science/Research
Classifier: Programming Language :: Python :: 3
Classifier: License :: OSI Approved :: MIT License
Requires-Python: >=3.10
License-File: LICENSE
Requires-Dist: dtcc-core
Requires-Dist: aiohttp==3.11.11
Requires-Dist: fastapi==0.115.6
Requires-Dist: folium==0.19.2
Requires-Dist: laspy==2.5.4
Requires-Dist: pyproj==3.7.0
Requires-Dist: requests==2.32.3
Requires-Dist: paramiko
Requires-Dist: geopandas
Requires-Dist: platformdirs>=4.3.6
Provides-Extra: test
Requires-Dist: pytest; extra == "test"
